LICENSE
README.md
setup.py
openredirect/main.py
openredirect.egg-info/PKG-INFO
openredirect.egg-info/SOURCES.txt
openredirect.egg-info/dependency_links.txt
openredirect.egg-info/entry_points.txt
openredirect.egg-info/requires.txt
openredirect.egg-info/top_level.txt
openredirect/includes/__init__.py
openredirect/includes/bot.py
openredirect/includes/filereader.py
openredirect/includes/scan.py
openredirect/includes/writefile.py
openredirect/utils/__init__.py
openredirect/utils/configure.py
openredirect/utils/const.py
openredirect/utils/helpers.py
openredirect/utils/status.py